hawc_client/__init__.py
hawc_client/animal.py
hawc_client/assessment.py
hawc_client/client.py
hawc_client/epi.py
hawc_client/epimeta.py
hawc_client/epiv2.py
hawc_client/exceptions.py
hawc_client/interactive.py
hawc_client/invitro.py
hawc_client/literature.py
hawc_client/riskofbias.py
hawc_client/session.py
hawc_client/study.py
hawc_client/summary.py
hawc_client/utils.py
hawc_client/vocab.py
hawc_client-2025.1.dist-info/licenses/LICENSE
hawc_client-2025.1.dist-info/WHEEL
hawc_client-2025.1.dist-info/METADATA
hawc_client-2025.1.dist-info/RECORD
