Metadata-Version: 2.4
Name: hawc-client
Version: 2025.1
Summary: A client for the Health Assessment Workspace Collaborative (HAWC).
Keywords: data visualization,epidemiology,risk assessment,systematic review,toxicology
Author-email: Andy Shapiro <shapiromatron@gmail.com>
Requires-Python: >=3.11
Classifier: Intended Audience :: Science/Research
Classifier: Programming Language :: Python :: 3.11
Classifier: Programming Language :: Python :: 3.12
Classifier: Programming Language :: Python :: 3.13
License-File: LICENSE
Requires-Dist: rapidfuzz
Requires-Dist: requests
Requires-Dist: pandas
Requires-Dist: playwright
Requires-Dist: tqdm
Project-URL: Bug Tracker, https://github.com/shapiromatron/hawc/issues
Project-URL: Changes, https://hawc.readthedocs.io/latest/client/#changelog
Project-URL: Documentation, https://hawc.readthedocs.io/client/
Project-URL: Source Code, https://github.com/shapiromatron/hawc
